arcane/snapchat/__init__.py
arcane/snapchat/const.py
arcane/snapchat/exceptions.py
arcane/snapchat/snapchat.py
arcane/snapchat/types.py
arcane_snapchat-0.2.1.dist-info/METADATA
arcane_snapchat-0.2.1.dist-info/WHEEL
arcane_snapchat-0.2.1.dist-info/RECORD
