Metadata-Version: 2.3
Name: arcane-snapchat
Version: 0.2.1
Summary: Helpers to request Snapchat API 
Author: Arcane
Author-email: product@wearcane.com
Requires-Python: >=3.6,<4.0
Classifier: Programming Language :: Python :: 3
Classifier: Programming Language :: Python :: 3.6
Classifier: Programming Language :: Python :: 3.7
Classifier: Programming Language :: Python :: 3.8
Classifier: Programming Language :: Python :: 3.9
Classifier: Programming Language :: Python :: 3.10
Classifier: Programming Language :: Python :: 3.11
Classifier: Programming Language :: Python :: 3.12
Classifier: Programming Language :: Python :: 3.13
Requires-Dist: arcane-core (>=1.6.0,<2.0.0)
Requires-Dist: backoff (>=1.10.0)
Requires-Dist: requests (>=2.0.0,<3.0.0)
